[
  {
    "id": "ChIJ2_5MrvHbwxURT1EZ6s2AKv8",
    "types": [
      "coffee_shop",
      "cafe",
      "food_store",
      "store",
      "food",
      "point_of_interest",
      "establishment"
    ],
    "formattedAddress": "Prince Saud Al Faisal, Al Khalidiyyah, Jeddah 23421, Saudi Arabia",
    "location": {
      "latitude": 21.5595289,
      "longitude": 39.132064299999996
    },
    "rating": 4.1,
    "userRatingCount": 2077,
    "displayName": {
      "text": "Jadeel",
      "languageCode": "en"
    },
    "takeout": true,
    "delivery": true,
    "primaryType": "coffee_shop",
    "paymentOptions": {
      "acceptsCreditCards": true,
      "acceptsCashOnly": false
    }
  },
  {
    "id": "ChIJ0V_DfDjPwxURh9RPejco7Lw",
    "types": [
      "coffee_shop",
      "cafe",
      "food_store",
      "store",
      "food",
      "point_of_interest",
      "establishment"
    ],
    "formattedAddress": "JBNA3060, King Abdallah Rd, 3060, Jeddah 23233, Saudi Arabia",
    "location": {
      "latitude": 21.511305999999998,
      "longitude": 39.228034
    },
    "rating": 4.3,
    "priceLevel": "PRICE_LEVEL_MODERATE",
    "userRatingCount": 3154,
    "displayName": {
      "text": "Half Million",
      "languageCode": "en"
    },
    "takeout": true,
    "delivery": true,
    "primaryType": "coffee_shop",
    "paymentOptions": {
      "acceptsCreditCards": true,
      "acceptsDebitCards": true,
      "acceptsCashOnly": false,
      "acceptsNfc": true
    }
  },
  {
    "id": "ChIJMxRSAcvbwxURzh0LM6UojiQ",
    "types": [
      "coffee_shop",
      "cafe",
      "food_store",
      "store",
      "food",
      "point_of_interest",
      "establishment"
    ],
    "formattedAddress": "2716-2604 Raoudat Sadhah, Al Khalidiyyah, Jeddah 23422, Saudi Arabia",
    "location": {
      "latitude": 21.5596461,
      "longitude": 39.131172899999996
    },
    "rating": 4.3,
    "priceLevel": "PRICE_LEVEL_MODERATE",
    "userRatingCount": 4578,
    "displayName": {
      "text": "Half Million",
      "languageCode": "en"
    },
    "takeout": true,
    "delivery": true,
    "primaryType": "coffee_shop",
    "paymentOptions": {
      "acceptsCreditCards": true,
      "acceptsDebitCards": true,
      "acceptsCashOnly": false,
      "acceptsNfc": true
    }
  },
  {
    "id": "ChIJIfOjkNHRwxURwHmw7cGRg9o",
    "types": [
      "coffee_shop",
      "cafe",
      "food_store",
      "store",
      "food",
      "point_of_interest",
      "establishment"
    ],
    "formattedAddress": "7404 Al Hasan, Al-Rehab, Jeddah 23343, Saudi Arabia",
    "location": {
      "latitude": 21.547314,
      "longitude": 39.235037000000005
    },
    "rating": 4.5,
    "priceLevel": "PRICE_LEVEL_MODERATE",
    "userRatingCount": 1807,
    "displayName": {
      "text": "Half Million",
      "languageCode": "en"
    },
    "delivery": true,
    "primaryType": "coffee_shop",
    "paymentOptions": {
      "acceptsCreditCards": true,
      "acceptsDebitCards": true,
      "acceptsCashOnly": true,
      "acceptsNfc": true
    }
  },
  {
    "id": "ChIJn8qq9vrbwxURiBlDpGUutTw",
    "types": [
      "coffee_shop",
      "cafe",
      "confectionery",
      "bakery",
      "food_store",
      "store",
      "food",
      "point_of_interest",
      "establishment"
    ],
    "formattedAddress": "Al Imam Malek, Ar Rawdah, Jeddah 23435, Saudi Arabia",
    "location": {
      "latitude": 21.572435799999997,
      "longitude": 39.153300699999996
    },
    "rating": 4.3,
    "userRatingCount": 3923,
    "displayName": {
      "text": "Got Cookie?",
      "languageCode": "en"
    },
    "takeout": true,
    "delivery": true,
    "primaryType": "bakery",
    "paymentOptions": {
      "acceptsCreditCards": true,
      "acceptsCashOnly": false
    }
  },
  {
    "id": "ChIJzQ2jne_bwxURIAEgsLIJ4wI",
    "types": [
      "coffee_shop",
      "cafe",
      "food_store",
      "store",
      "food",
      "point_of_interest",
      "establishment"
    ],
    "formattedAddress": "2489 Saqer Qouraish, As Salamah, Jeddah 23436, Saudi Arabia",
    "location": {
      "latitude": 21.5815758,
      "longitude": 39.1475192
    },
    "rating": 4.3,
    "userRatingCount": 1369,
    "displayName": {
      "text": "Sorted Speciality Coffee by SORT",
      "languageCode": "en"
    },
    "takeout": true,
    "delivery": true,
    "primaryType": "coffee_shop",
    "paymentOptions": {
      "acceptsCreditCards": true,
      "acceptsCashOnly": false
    }
  },
  {
    "id": "ChIJn1jNV-PFwxURlu4mNAHqh40",
    "types": [
      "coffee_shop",
      "cafe",
      "food_store",
      "store",
      "food",
      "point_of_interest",
      "establishment"
    ],
    "formattedAddress": "Tahlia Street\u060c 6631 Abdullah Al Matari\u060c Al Andalus, Jeddah 23322, Saudi Arabia",
    "location": {
      "latitude": 21.5472604,
      "longitude": 39.1495057
    },
    "rating": 4,
    "userRatingCount": 4006,
    "displayName": {
      "text": "Sculpture Caf\u00e9",
      "languageCode": "en"
    }
  },
  {
    "id": "ChIJr3lRboHZwxURI329Nkelz-c",
    "types": [
      "coffee_shop",
      "cafe",
      "food_store",
      "store",
      "food",
      "point_of_interest",
      "establishment"
    ],
    "formattedAddress": "King Abdulaziz Branch Rd, Al Basateen, Jeddah 23718, Saudi Arabia",
    "location": {
      "latitude": 21.689076,
      "longitude": 39.110293999999996
    },
    "rating": 4.3,
    "priceLevel": "PRICE_LEVEL_MODERATE",
    "userRatingCount": 2988,
    "displayName": {
      "text": "Half Million",
      "languageCode": "en"
    },
    "takeout": true,
    "delivery": true,
    "primaryType": "coffee_shop",
    "paymentOptions": {
      "acceptsCreditCards": true,
      "acceptsDebitCards": true,
      "acceptsCashOnly": false,
      "acceptsNfc": true
    }
  },
  {
    "id": "ChIJGR2A0zTRwxURu9-RxspvrAI",
    "types": [
      "coffee_shop",
      "cafe",
      "food_store",
      "store",
      "food",
      "point_of_interest",
      "establishment"
    ],
    "formattedAddress": "Al Kuwait, Al Faisaliyyah, Jeddah 23442, Saudi Arabia",
    "location": {
      "latitude": 21.5699673,
      "longitude": 39.1705435
    },
    "rating": 4.7,
    "userRatingCount": 2058,
    "displayName": {
      "text": "White Heart",
      "languageCode": "en"
    },
    "takeout": true,
    "delivery": true,
    "primaryType": "coffee_shop",
    "paymentOptions": {
      "acceptsCreditCards": true,
      "acceptsDebitCards": true,
      "acceptsCashOnly": false,
      "acceptsNfc": true
    }
  },
  {
    "id": "ChIJ9fRRP43bwxUR29w4vDKsJIA",
    "types": [
      "coffee_shop",
      "cafe",
      "bakery",
      "food_store",
      "store",
      "food",
      "point_of_interest",
      "establishment"
    ],
    "formattedAddress": "3362 Hiraa St - Ash Shati District, Jeddah 23514 - 7750\u060c Ash Shati, Jeddah 23514, Saudi Arabia",
    "location": {
      "latitude": 21.605833999999998,
      "longitude": 39.1181972
    },
    "rating": 4.4,
    "userRatingCount": 2149,
    "displayName": {
      "text": "Raksha",
      "languageCode": "en"
    },
    "takeout": true,
    "delivery": false,
    "primaryType": "coffee_shop",
    "paymentOptions": {
      "acceptsCreditCards": true,
      "acceptsCashOnly": true,
      "acceptsNfc": true
    }
  },
  {
    "id": "ChIJK_UAJAXbwxURSYj7kzsMQU8",
    "types": [
      "coffee_shop",
      "cafe",
      "wholesaler",
      "food_store",
      "store",
      "food",
      "point_of_interest",
      "establishment"
    ],
    "formattedAddress": "Abdulrahman aldakhel street, An Nahdah, Jeddah 23326, Saudi Arabia",
    "location": {
      "latitude": 21.618035900000002,
      "longitude": 39.131408
    },
    "rating": 4.4,
    "userRatingCount": 1662,
    "displayName": {
      "text": "Camel Step",
      "languageCode": "en"
    },
    "takeout": true,
    "delivery": true
  },
  {
    "id": "ChIJuVGoFgDbwxURI1-khkNSaZA",
    "types": [
      "cafe",
      "coffee_shop",
      "wholesaler",
      "dessert_shop",
      "confectionery",
      "food_store",
      "store",
      "food",
      "point_of_interest",
      "establishment"
    ],
    "formattedAddress": "Prince Sultan Rd, An Nahdah, Jeddah 23523, Saudi Arabia",
    "location": {
      "latitude": 21.6274832,
      "longitude": 39.1350841
    },
    "rating": 4.6,
    "priceLevel": "PRICE_LEVEL_MODERATE",
    "userRatingCount": 899,
    "displayName": {
      "text": "Kiffa Roasters",
      "languageCode": "en"
    },
    "takeout": true,
    "delivery": true,
    "primaryType": "cafe",
    "paymentOptions": {
      "acceptsCreditCards": true,
      "acceptsCashOnly": false
    }
  },
  {
    "id": "ChIJo1a1n3FjwRURwoEfwfKguYc",
    "types": [
      "coffee_shop",
      "cafe",
      "food_store",
      "store",
      "food",
      "point_of_interest",
      "establishment"
    ],
    "formattedAddress": "Abhur Al Junoobiyah, Jeddah 23734, Saudi Arabia",
    "location": {
      "latitude": 21.757245299999997,
      "longitude": 39.136083600000006
    },
    "rating": 4.1,
    "userRatingCount": 1926,
    "displayName": {
      "text": "ROW",
      "languageCode": "en"
    },
    "takeout": true,
    "delivery": true,
    "primaryType": "coffee_shop",
    "paymentOptions": {
      "acceptsCreditCards": true,
      "acceptsCashOnly": false
    }
  },
  {
    "id": "ChIJOz1ETDfRwxUR-OneEv3-A9c",
    "types": [
      "coffee_shop",
      "cafe",
      "food_store",
      "store",
      "food",
      "point_of_interest",
      "establishment"
    ],
    "formattedAddress": "JDBA6938\u060c 6938\u060c 4097 King Fahd Br Rd, Al Faisaliyyah, Jeddah 23441, Saudi Arabia",
    "location": {
      "latitude": 21.5641641,
      "longitude": 39.185795299999995
    },
    "rating": 3.5,
    "userRatingCount": 1156,
    "displayName": {
      "text": "36 \u0643\u0627\u0641\u064a\u0647 \u0648\u0644\u0627\u0648\u0646\u062c",
      "languageCode": "ar"
    },
    "takeout": true,
    "delivery": false,
    "primaryType": "coffee_shop",
    "paymentOptions": {
      "acceptsCreditCards": true,
      "acceptsDebitCards": true,
      "acceptsCashOnly": false,
      "acceptsNfc": true
    }
  },
  {
    "id": "ChIJsR3w4zfQwxURcy-90KDCSKI",
    "types": [
      "furniture_store",
      "home_improvement_store",
      "cafe",
      "home_goods_store",
      "store",
      "food",
      "point_of_interest",
      "establishment"
    ],
    "formattedAddress": "JCZA9060\u060c 3286 King Fahd Br Rd, Aziziyah, 9060\u060c Jeddah 23334, Saudi Arabia",
    "location": {
      "latitude": 21.5577821,
      "longitude": 39.1865513
    },
    "rating": 4,
    "userRatingCount": 10119,
    "displayName": {
      "text": "Abyat",
      "languageCode": "en"
    },
    "delivery": true,
    "primaryType": "furniture_store",
    "paymentOptions": {
      "acceptsCreditCards": true,
      "acceptsDebitCards": true,
      "acceptsCashOnly": false,
      "acceptsNfc": true
    }
  },
  {
    "id": "ChIJkfEamqnZwxURRKgokm_QwMo",
    "types": [
      "cafe",
      "food",
      "point_of_interest",
      "establishment"
    ],
    "formattedAddress": "Prince Sultan Rd, Al Mohammadiyyah, Jeddah 23623, Saudi Arabia",
    "location": {
      "latitude": 21.6460111,
      "longitude": 39.1284589
    },
    "rating": 4.6,
    "priceLevel": "PRICE_LEVEL_INEXPENSIVE",
    "userRatingCount": 1257,
    "displayName": {
      "text": "(\u0627\u0644\u0645\u062d\u0645\u062f\u064a\u0629) BART - \u0628\u0627\u0631\u062a",
      "languageCode": "en"
    },
    "takeout": true,
    "delivery": true,
    "primaryType": "cafe",
    "paymentOptions": {
      "acceptsCreditCards": true,
      "acceptsCashOnly": false
    }
  },
  {
    "id": "ChIJH4rdJf_ZwxURpeeYT0gCGPQ",
    "types": [
      "cafe",
      "coffee_shop",
      "food_store",
      "store",
      "food",
      "point_of_interest",
      "establishment"
    ],
    "formattedAddress": "King Abdul Aziz Rd, Al Mohammadiyyah, Jeddah 23617, Saudi Arabia",
    "location": {
      "latitude": 21.6483407,
      "longitude": 39.112127400000006
    },
    "rating": 4.1,
    "userRatingCount": 1906,
    "displayName": {
      "text": "Urth Caff\u00e9",
      "languageCode": "en"
    },
    "takeout": true,
    "delivery": true,
    "primaryType": "cafe",
    "paymentOptions": {
      "acceptsCreditCards": true,
      "acceptsDebitCards": true,
      "acceptsCashOnly": false,
      "acceptsNfc": true
    }
  },
  {
    "id": "ChIJpXJpnyDXwxURJeklTobm1XU",
    "types": [
      "coffee_shop",
      "cafe",
      "food_store",
      "store",
      "food",
      "point_of_interest",
      "establishment"
    ],
    "formattedAddress": "3722 Hira St, Al Marwah, Jeddah 23544, Saudi Arabia",
    "location": {
      "latitude": 21.6224287,
      "longitude": 39.198747499999996
    },
    "rating": 4.1,
    "priceLevel": "PRICE_LEVEL_MODERATE",
    "userRatingCount": 1160,
    "displayName": {
      "text": "Half Million",
      "languageCode": "en"
    },
    "takeout": true,
    "delivery": true,
    "primaryType": "coffee_shop",
    "paymentOptions": {
      "acceptsCreditCards": true,
      "acceptsDebitCards": true,
      "acceptsCashOnly": true,
      "acceptsNfc": true
    }
  },
  {
    "id": "ChIJlVWajyTbwxURgsDCrDVqkRI",
    "types": [
      "coffee_shop",
      "cafe",
      "food_store",
      "store",
      "food",
      "point_of_interest",
      "establishment"
    ],
    "formattedAddress": "Al Zahra, Jeddah 23424, Saudi Arabia",
    "location": {
      "latitude": 21.572449499999998,
      "longitude": 39.1319325
    },
    "rating": 3.6,
    "userRatingCount": 889,
    "displayName": {
      "text": "JOININ",
      "languageCode": "en"
    },
    "takeout": true,
    "delivery": true,
    "primaryType": "coffee_shop",
    "paymentOptions": {
      "acceptsCreditCards": true,
      "acceptsCashOnly": false
    }
  },
  {
    "id": "ChIJkxGUFvHXwxURjmRjYO4F5aU",
    "types": [
      "hotel",
      "banquet_hall",
      "auditorium",
      "wedding_venue",
      "atm",
      "coffee_shop",
      "cafe",
      "event_venue",
      "lodging",
      "food_store",
      "store",
      "sports_club",
      "finance",
      "restaurant",
      "food",
      "point_of_interest",
      "establishment"
    ],
    "formattedAddress": "JFRA8061\u060c 8061 2133\u060c \u062d\u064a, \u0631\u0628\u0627\u062d \u0627\u0644\u0644\u062e\u0645\u064a\u060c Al Rayaan, Jeddah 23642, Saudi Arabia",
    "location": {
      "latitude": 21.6655355,
      "longitude": 39.204732799999995
    },
    "rating": 4.3,
    "userRatingCount": 1711,
    "displayName": {
      "text": "Donatello Hotel",
      "languageCode": "en"
    },
    "primaryType": "hotel",
    "paymentOptions": {
      "acceptsCreditCards": true
    }
  }
]